[
    {
        "nome": "Ana Beatriz",
        "telefone": "+5511912345678",
        "interesse": "criptomoedas",
        "orçamento": 1500,
        "sugestao": "O Bitcoin está estável em $109008.10. Acompanhe o mercado antes de tomar decisões."
    },
    {
        "nome": "Carlos Eduardo",
        "telefone": "+5521998765432",
        "interesse": "criptomoedas",
        "orçamento": 3000,
        "sugestao": "O Bitcoin está estável em $109008.10. Acompanhe o mercado antes de tomar decisões."
    },
    {
        "nome": "Lucas Martins",
        "telefone": "+5561976543210",
        "interesse": "criptomoedas",
        "orçamento": 2000,
        "sugestao": "O Bitcoin está estável em $109008.40. Acompanhe o mercado antes de tomar decisões."
    },
    {
        "nome": "Gabriel Costa",
        "telefone": "+5571912223344",
        "interesse": "viagem",
        "orçamento": 4000,
        "sugestao": "A temperatura está agradável (19.0°C). Um ótimo dia para sair!"
    },
    {
        "nome": "Isabela Rocha",
        "telefone": "+5581988887777",
        "interesse": "cachorros",
        "orçamento": 2500,
        "sugestao": "One of the single best things about being an adult, is being able to buy as much LEGO as you want."
    },
    {
        "nome": "Pedro Henrique",
        "telefone": "+5591999998888",
        "interesse": "clima",
        "orçamento": 1800,
        "sugestao": "A temperatura está agradável (19.0°C). Um ótimo dia para sair!"
    }
]